{"cameraMode":{"drawMode":0,"name":"Shaded","section":"Shading Mode"},"sceneLighting":true,"audioPlay":false,"sceneViewState":{"showFog":true,"showMaterialUpdate":false,"showSkybox":true,"showFlares":true,"showImageEffects":true,"showParticleSystems":true},"in2DMode":false,"pivot":{"x":-1.72609281539917,"y":14.530537605285645,"z":6.990237712860107},"rotation":{"x":0.0009928758954629303,"y":0.8310574293136597,"z":-0.5562103390693665,"w":0.0015018393751233817},"size":1.4930955171585084,"orthographic":false}